Metadata-Version: 2.1
Name: proteuscmd
Version: 0.7
Summary: A command line interface to modify DNS entries in Proteus.
Home-page: https://github.com/virtUOS/proteuscmd
Author: Lars Kiesow
Author-email: lkiesow@uos.de
License: MIT
